PACKAGE_DJANGO/__init__.py
PACKAGE_DJANGO/__main__.py
PACKAGE_DJANGO/gen.py
create_newapp-0.3.dist-info/METADATA
create_newapp-0.3.dist-info/WHEEL
create_newapp-0.3.dist-info/entry_points.txt
create_newapp-0.3.dist-info/top_level.txt
create_newapp-0.3.dist-info/RECORD
