Metadata-Version: 2.4
Name: create_Newapp
Version: 0.3
Summary: Un outil pour créer une application Django complète automatiquement.
Author: Tieba
Classifier: Programming Language :: Python :: 3
Classifier: Framework :: Django
Requires-Python: >=3.6
Dynamic: author
Dynamic: classifier
Dynamic: description
Dynamic: description-content-type
Dynamic: requires-python
Dynamic: summary
